databench_eval/__init__.py
databench_eval/eval.py
databench_eval/run.py
databench_eval/utils.py
databench_eval-4.0.1.dist-info/LICENSE
databench_eval-4.0.1.dist-info/METADATA
databench_eval-4.0.1.dist-info/WHEEL
databench_eval-4.0.1.dist-info/top_level.txt
databench_eval-4.0.1.dist-info/RECORD
