Metadata-Version: 2.2
Name: databench_eval
Version: 4.0.1
Summary: Evaluation framework for DataBench
Home-page: https://github.com/jorses/databench
Author: jorses
Author-email: jorgeosesgrijalba@gmail.com
Project-URL: Homepage, https://github.com/jorses/databench
Project-URL: Issues, https://github.com/jorses/databench/issues
Classifier: Programming Language :: Python :: 3
Classifier: License :: OSI Approved :: MIT License
Classifier: Operating System :: OS Independent
Requires-Python: >=3.8
License-File: LICENSE
Requires-Dist: datasets
Requires-Dist: tqdm
Requires-Dist: pandas
Requires-Dist: numpy
Dynamic: author
Dynamic: author-email
Dynamic: classifier
Dynamic: description
Dynamic: description-content-type
Dynamic: home-page
Dynamic: project-url
Dynamic: requires-dist
Dynamic: requires-python
Dynamic: summary
